esis/es.py
esis/util.py
esis/cli.py
esis/__init__.py
esis/fs.py
esis/db.py
esis-0.2.0.dist-info/pbr.json
esis-0.2.0.dist-info/entry_points.txt
esis-0.2.0.dist-info/WHEEL
esis-0.2.0.dist-info/METADATA
esis-0.2.0.dist-info/top_level.txt
esis-0.2.0.dist-info/DESCRIPTION.rst
esis-0.2.0.dist-info/metadata.json
esis-0.2.0.dist-info/RECORD
