Metadata-Version: 2.0
Name: esis
Version: 0.2.0
Summary: Elastic Search Index & Search
Home-page: https://github.com/jcollado/esis
Author: Javier Collado
Author-email: jcollado@nowsecure.com
License: MIT
Keywords: elastic search index sqlite
Platform: UNKNOWN
Classifier: Development Status :: 3 - Alpha
Classifier: Intended Audience :: Developers
Classifier: License :: OSI Approved :: MIT License
Classifier: Natural Language :: English
Classifier: Programming Language :: Python :: 2.7
Requires-Dist: SQLAlchemy
Requires-Dist: python-dateutil
Requires-Dist: python-magic
Requires-Dist: elasticsearch
